pr_insight/__init__.py
pr_insight/cli.py
pr_insight/cli_pip.py
pr_insight/config_loader.py
pr_insight/algo/__init__.py
pr_insight/algo/file_filter.py
pr_insight/algo/git_patch_processing.py
pr_insight/algo/language_handler.py
pr_insight/algo/pr_processing.py
pr_insight/algo/token_handler.py
pr_insight/algo/types.py
pr_insight/algo/utils.py
pr_insight/algo/ai_handlers/base_ai_handler.py
pr_insight/algo/ai_handlers/langchain_ai_handler.py
pr_insight/algo/ai_handlers/litellm_ai_handler.py
pr_insight/algo/ai_handlers/openai_ai_handler.py
pr_insight/git_providers/__init__.py
pr_insight/git_providers/azuredevops_provider.py
pr_insight/git_providers/bitbucket_provider.py
pr_insight/git_providers/bitbucket_server_provider.py
pr_insight/git_providers/codecommit_client.py
pr_insight/git_providers/codecommit_provider.py
pr_insight/git_providers/gerrit_provider.py
pr_insight/git_providers/git_provider.py
pr_insight/git_providers/github_provider.py
pr_insight/git_providers/gitlab_provider.py
pr_insight/git_providers/local_git_provider.py
pr_insight/git_providers/utils.py
pr_insight/identity_providers/__init__.py
pr_insight/identity_providers/default_identity_provider.py
pr_insight/identity_providers/identity_provider.py
pr_insight/insight/__init__.py
pr_insight/insight/pr_insight.py
pr_insight/log/__init__.py
pr_insight/secret_providers/__init__.py
pr_insight/secret_providers/google_cloud_storage_secret_provider.py
pr_insight/secret_providers/secret_provider.py
pr_insight/servers/__init__.py
pr_insight/servers/azuredevops_server_webhook.py
pr_insight/servers/bitbucket_app.py
pr_insight/servers/bitbucket_server_webhook.py
pr_insight/servers/gerrit_server.py
pr_insight/servers/github_action_runner.py
pr_insight/servers/github_app.py
pr_insight/servers/github_polling.py
pr_insight/servers/gitlab_webhook.py
pr_insight/servers/gunicorn_config.py
pr_insight/servers/help.py
pr_insight/servers/serverless.py
pr_insight/servers/utils.py
pr_insight/settings/.secrets_template.toml
pr_insight-0.2.1.dist-info/LICENSE
pr_insight-0.2.1.dist-info/METADATA
pr_insight-0.2.1.dist-info/WHEEL
pr_insight-0.2.1.dist-info/entry_points.txt
pr_insight-0.2.1.dist-info/top_level.txt
pr_insight-0.2.1.dist-info/RECORD
